mental_health_app/__init__.py
mental_health_app/main.py
mental_health_app/test.py
mental_health_app-0.6.dist-info/licenses/LICENSE
tests/__init__.py
tests/test_facemind.py
mental_health_app-0.6.dist-info/METADATA
mental_health_app-0.6.dist-info/WHEEL
mental_health_app-0.6.dist-info/entry_points.txt
mental_health_app-0.6.dist-info/top_level.txt
mental_health_app-0.6.dist-info/RECORD
