Metadata-Version: 2.4
Name: mental_health_app
Version: 0.6
Summary: A mental health prediction app using facial analysis.
Home-page: https://github.com/galihru/facemind
Author: GALIH RIDHO UTOMO. Ana Maulida
Author-email: GALIH RIDHO UTOMO <g4lihru@students.unnes.ac.id>, Ana Maulida <anamaulida@students.unnes.ac.id>
Project-URL: Documentation, https://github.com/galihru/facemind/README.md
Project-URL: Source, https://github.com/galihru/facemind
Project-URL: Homepage, https://galihru.github.io/facemind/
Classifier: Programming Language :: Python :: 3
Classifier: License :: OSI Approved :: MIT License
Classifier: Operating System :: OS Independent
Requires-Python: >=3.6
License-File: LICENSE
Requires-Dist: opencv-python
Requires-Dist: numpy
Requires-Dist: pandas
Requires-Dist: matplotlib
Requires-Dist: mediapipe
Requires-Dist: selenium
Requires-Dist: PyQt5
Dynamic: author
Dynamic: home-page
Dynamic: license-file
Dynamic: requires-python
